taylorist_langchain/__init__.py
taylorist_langchain/__main__.py
taylorist_langchain/integrations/llm/__init__.py
taylorist_langchain/integrations/llm/llm_taylorist_langchain.py
taylorist_langchain/integrations/stt/__init__.py
taylorist_langchain/integrations/stt/stt_taylorist_langchain.py
taylorist_langchain/integrations/tts/__init__.py
taylorist_langchain/integrations/tts/tts_taylorist_langchain.py
taylorist_langchain-0.0.2.dist-info/METADATA
taylorist_langchain-0.0.2.dist-info/WHEEL
taylorist_langchain-0.0.2.dist-info/top_level.txt
taylorist_langchain-0.0.2.dist-info/RECORD
