Metadata-Version: 2.4
Name: taylorist-langchain
Version: 0.0.2
Home-page: https://github.com/umutkrts07/taylorist-langchain
Author: umutkrts
Project-URL: Bug Tracker, https://github.com/umutkrts07/taylorist-langchain/issues
Project-URL: Source Code, https://github.com/umutkrts07/taylorist-langchain
Classifier: Programming Language :: Python :: 3
Classifier: License :: OSI Approved :: MIT License
Classifier: Operating System :: OS Independent
Requires-Python: >=3.8
Requires-Dist: taylorist>=0.1.0
Requires-Dist: langchain-core>=0.3.70
Dynamic: author
Dynamic: classifier
Dynamic: description
Dynamic: description-content-type
Dynamic: home-page
Dynamic: project-url
Dynamic: requires-dist
Dynamic: requires-python
